ebisusbay/__init__.py
ebisusbay/api.py
ebisusbay-0.1.3.dist-info/LICENSE
ebisusbay-0.1.3.dist-info/METADATA
ebisusbay-0.1.3.dist-info/WHEEL
ebisusbay-0.1.3.dist-info/top_level.txt
ebisusbay-0.1.3.dist-info/RECORD
