Metadata-Version: 2.1
Name: ebisusbay
Version: 0.1.3
Summary: Python Wrapper for ebisusbay.com API
Home-page: https://github.com/JulienCoutault/EbisusBay-API
Author: Programmateur01
Author-email: ebisusbay-api@juliencoutault.fr
License: MIT
Project-URL: Source, https://github.com/JulienCoutault/EbisusBay-API
Keywords: Cronos,API,CRO,Blockchain,NFT,ebisusbay.com
Classifier: Development Status :: 3 - Alpha
Classifier: Intended Audience :: Developers
Classifier: Topic :: Software Development :: Build Tools
Classifier: License :: OSI Approved :: MIT License
Classifier: Programming Language :: Python :: 3
License-File: LICENSE
Requires-Dist: requests
